Metadata-Version: 2.1
Name: ebuild
Version: 1.0.0
Summary: Easily cross compile your C/C++ projects or create your SDK
Home-page: https://github.com/neutree/ebuild
Author: Neutree
Author-email: CZD666666@gmail.com
License: MIT
Keywords: embeded,cross compile,build system
Classifier: Development Status :: 5 - Production/Stable
Classifier: Intended Audience :: Developers
Classifier: Intended Audience :: Education
Classifier: Intended Audience :: Science/Research
Classifier: Topic :: Software Development :: Embedded Systems
Classifier: License :: OSI Approved :: MIT License
Classifier: Programming Language :: Python :: 3
License-File: LICENSE
